{
    "os": "Linux-4.18.0-553.27.1.el8_10.x86_64-x86_64-with-glibc2.28",
    "python": "3.9.12",
    "heartbeatAt": "2024-12-11T07:11:24.720481",
    "startedAt": "2024-12-11T07:11:24.402456",
    "docker": null,
    "cuda": null,
    "args": [
        "--pretrained_model_name_or_path=stabilityai/stable-video-diffusion-img2vid",
        "--output_dir=/fs/nexus-scratch/sjxu/Model_out/model_add_light",
        "--csv_path=/fs/nexus-scratch/sjxu/WebVid/blender.csv",
        "--video_folder=/fs/nexus-scratch/sjxu/WebVid/blender/img",
        "--condition_folder=/fs/nexus-scratch/sjxu/WebVid/blender/shd",
        "--motion_folder=/fs/nexus-scratch/sjxu/WebVid/blender/motion",
        "--validation_image_folder=/fs/nexus-scratch/sjxu/svd-temporal-controlnet/validation_demo/img_blender",
        "--validation_control_folder=/fs/nexus-scratch/sjxu/svd-temporal-controlnet/validation_demo/shd_blender",
        "--width=512",
        "--height=512",
        "--learning_rate=1e-4",
        "--per_gpu_batch_size=1",
        "--num_train_epochs=120",
        "--mixed_precision=fp16",
        "--gradient_accumulation_steps=16",
        "--checkpointing_steps=500",
        "--validation_steps=200",
        "--gradient_checkpointing",
        "--checkpoints_total_limit=1",
        "--report_to=wandb",
        "--dropout_rgb=0.1",
        "--sample_n_frames=6",
        "--num_frames=6",
        "--inject_lighting_direction",
        "--concat_depth_maps"
    ],
    "state": "running",
    "program": "/fs/nexus-scratch/sjxu/svd-temporal-controlnet/train_svd_controlnet.py",
    "codePathLocal": "train_svd_controlnet.py",
    "codePath": "train_svd_controlnet.py",
    "git": {
        "remote": "git@github.com:jayhsu0627/SVD_ControlNet_Relight.git",
        "commit": "0e8278eb68d9589b90e2c229cec2290930e10019"
    },
    "email": null,
    "root": "/fs/nexus-scratch/sjxu/svd-temporal-controlnet",
    "host": "tron60.umiacs.umd.edu",
    "username": "sjxu",
    "executable": "/fs/nexus-scratch/sjxu/miniconda3/envs/svd_control/bin/python",
    "cpu_count": 48,
    "cpu_count_logical": 48,
    "cpu_freq": {
        "current": 2317.6758958333335,
        "min": 1500.0,
        "max": 2300.0
    },
    "cpu_freq_per_core": [
        {
            "current": 2300.0,
            "min": 1500.0,
            "max": 2300.0
        },
        {
            "current": 2300.0,
            "min": 1500.0,
            "max": 2300.0
        },
        {
            "current": 2300.0,
            "min": 1500.0,
            "max": 2300.0
        },
        {
            "current": 2300.0,
            "min": 1500.0,
            "max": 2300.0
        },
        {
            "current": 2300.0,
            "min": 1500.0,
            "max": 2300.0
        },
        {
            "current": 2300.0,
            "min": 1500.0,
            "max": 2300.0
        },
        {
            "current": 2300.0,
            "min": 1500.0,
            "max": 2300.0
        },
        {
            "current": 2300.0,
            "min": 1500.0,
            "max": 2300.0
        },
        {
            "current": 2300.0,
            "min": 1500.0,
            "max": 2300.0
        },
        {
            "current": 3148.443,
            "min": 1500.0,
            "max": 2300.0
        },
        {
            "current": 2300.0,
            "min": 1500.0,
            "max": 2300.0
        },
        {
            "current": 2300.0,
            "min": 1500.0,
            "max": 2300.0
        },
        {
            "current": 2300.0,
            "min": 1500.0,
            "max": 2300.0
        },
        {
            "current": 2300.0,
            "min": 1500.0,
            "max": 2300.0
        },
        {
            "current": 2300.0,
            "min": 1500.0,
            "max": 2300.0
        },
        {
            "current": 2300.0,
            "min": 1500.0,
            "max": 2300.0
        },
        {
            "current": 2300.0,
            "min": 1500.0,
            "max": 2300.0
        },
        {
            "current": 2300.0,
            "min": 1500.0,
            "max": 2300.0
        },
        {
            "current": 2300.0,
            "min": 1500.0,
            "max": 2300.0
        },
        {
            "current": 2300.0,
            "min": 1500.0,
            "max": 2300.0
        },
        {
            "current": 2300.0,
            "min": 1500.0,
            "max": 2300.0
        },
        {
            "current": 2300.0,
            "min": 1500.0,
            "max": 2300.0
        },
        {
            "current": 2300.0,
            "min": 1500.0,
            "max": 2300.0
        },
        {
            "current": 2300.0,
            "min": 1500.0,
            "max": 2300.0
        },
        {
            "current": 2300.0,
            "min": 1500.0,
            "max": 2300.0
        },
        {
            "current": 2300.0,
            "min": 1500.0,
            "max": 2300.0
        },
        {
            "current": 2300.0,
            "min": 1500.0,
            "max": 2300.0
        },
        {
            "current": 2300.0,
            "min": 1500.0,
            "max": 2300.0
        },
        {
            "current": 2300.0,
            "min": 1500.0,
            "max": 2300.0
        },
        {
            "current": 2300.0,
            "min": 1500.0,
            "max": 2300.0
        },
        {
            "current": 2300.0,
            "min": 1500.0,
            "max": 2300.0
        },
        {
            "current": 2300.0,
            "min": 1500.0,
            "max": 2300.0
        },
        {
            "current": 2300.0,
            "min": 1500.0,
            "max": 2300.0
        },
        {
            "current": 2300.0,
            "min": 1500.0,
            "max": 2300.0
        },
        {
            "current": 2300.0,
            "min": 1500.0,
            "max": 2300.0
        },
        {
            "current": 2300.0,
            "min": 1500.0,
            "max": 2300.0
        },
        {
            "current": 2300.0,
            "min": 1500.0,
            "max": 2300.0
        },
        {
            "current": 2300.0,
            "min": 1500.0,
            "max": 2300.0
        },
        {
            "current": 2300.0,
            "min": 1500.0,
            "max": 2300.0
        },
        {
            "current": 2300.0,
            "min": 1500.0,
            "max": 2300.0
        },
        {
            "current": 2300.0,
            "min": 1500.0,
            "max": 2300.0
        },
        {
            "current": 2300.0,
            "min": 1500.0,
            "max": 2300.0
        },
        {
            "current": 2300.0,
            "min": 1500.0,
            "max": 2300.0
        },
        {
            "current": 2300.0,
            "min": 1500.0,
            "max": 2300.0
        },
        {
            "current": 2300.0,
            "min": 1500.0,
            "max": 2300.0
        },
        {
            "current": 2300.0,
            "min": 1500.0,
            "max": 2300.0
        },
        {
            "current": 2300.0,
            "min": 1500.0,
            "max": 2300.0
        },
        {
            "current": 2300.0,
            "min": 1500.0,
            "max": 2300.0
        }
    ],
    "disk": {
        "/": {
            "total": 39.043426513671875,
            "used": 14.046058654785156
        }
    },
    "gpu": "NVIDIA RTX A5000",
    "gpu_count": 1,
    "gpu_devices": [
        {
            "name": "NVIDIA RTX A5000",
            "memory_total": 25757220864
        }
    ],
    "memory": {
        "total": 251.24996948242188
    }
}
